setup.py
atomia_client/__init__.py
atomia_client/atomia_actions.py
atomia_client/atomia_entities.py
atomia_client/atomia_operations.py
atomia_client.egg-info/PKG-INFO
atomia_client.egg-info/SOURCES.txt
atomia_client.egg-info/dependency_links.txt
atomia_client.egg-info/top_level.txt
atomia_client/pysimplesoap_atomia/__init__.py
atomia_client/pysimplesoap_atomia/client.py
atomia_client/pysimplesoap_atomia/server.py
atomia_client/pysimplesoap_atomia/simplexml.py
atomia_client/pysimplesoap_atomia/socks.py