Metadata-Version: 1.0
Name: atomia-client
Version: 12.5.0
Summary: Client library for Atomia Automation Server.
Home-page: http://www.atomia.com/
Author: Atomia AB
Author-email: thorsten@atomia.com
License: Atomia
Keywords: atomia automationserver server
Platform: UNKNOWN
Classifier: Development Status :: 4 - Beta
Classifier: Topic :: Internet
Classifier: Programming Language :: Python
